<?xml version="1.0" encoding="UTF-8"?>
	<!-- POSC License Agreement
	This file is distributed under the POSC License Agreement at
	http://www.posc.org/about/license.shtml.
	Use of this file constitutes agreement with the POSC License Agreement.
	-->
<logs 
	xmlns="http://www.witsml.org/schemas/120" 
	xmlns:xsi="http://www.w3.org/2001/XMLSchema-instance" 
	xsi:schemaLocation="http://www.witsml.org/schemas/120 
	http://www.witsml.org/schemas/120/obj_log.xsd" 
	version="1.2.0">
  <log uidWell="Well123" uidWellbore="6KFSJ18" uidLog="228KKJH14" uidSource="Server1">
    <nameWell>DemoWell2</nameWell>
    <nameWellbore>Wellbore3</nameWellbore>
    <nameLog>Caliper</nameLog>
    <logHeader>
      <serviceCompany>ServiceCompany</serviceCompany>
      <runNumber>10</runNumber>
      <creationDate>2007-02-17T11:22:33.0000000+01:00</creationDate>
      <indexType>Depth</indexType>
      <startIndex>2933.754</startIndex>
      <endIndex>3317.805</endIndex>
      <direction>Increasing</direction>
      <indexCurve>Depth</indexCurve>
      <stepIncrement>0</stepIncrement>
      <indexUnits>m</indexUnits>
      <nullValue>-999.25</nullValue>
      <uomNamingSystem>RP66</uomNamingSystem>
      <logCurveInfo>
        <mnemonic>Depth</mnemonic>
        <unit>m</unit>
        <startIndex>2933.754</startIndex>
        <endIndex>3317.805</endIndex>
        <columnIndex>1</columnIndex>
        <curveDescription>The mnemonic of the index curve</curveDescription>
        <sensorOffset>0</sensorOffset>
        <traceState>Raw</traceState>
        <typeLogData>Double</typeLogData>
      </logCurveInfo>
      <logCurveInfo>
        <mnemonic>CALCX</mnemonic>
        <unit>in</unit>
        <nullValue>-999.25</nullValue>
        <startIndex>2933.754</startIndex>
        <endIndex>3317.805</endIndex>
        <columnIndex>2</columnIndex>
        <curveDescription>Acoustic Caliper - Corrected</curveDescription>
        <typeLogData>Double</typeLogData>
      </logCurveInfo>
    </logHeader>
<logData>
<data>2933.754,10.5</data>
<data>2933.754,11.594</data>
<data>2933.754,8</data>
<data>2933.754,8.625</data>
<data>2933.754,13.625</data>
<data>2933.754,8.625</data>
<data>2933.754,13.625</data>
<data>2933.754,8.625</data>
<data>2933.754,8.469</data>
<data>2933.754,8.469</data>
<data>2933.754,8.469</data>
<data>2934.744,8.625</data>
<data>2938.509,8.625</data>
<data>2939.475,8.625</data>
<data>2940.353,14.406</data>
<data>2942.623,8.469</data>
<data>2942.932,8.52</data>
<data>2943.141,8.52</data>
<data>2943.523,8.358</data>
<data>2943.992,8.358</data>
<data>2944.553,8.52</data>
<data>2945.873,8.682</data>
<data>2947.006,8.682</data>
<data>2947.605,8.682</data>
<data>2948.788,9.006</data>
<data>2949.827,8.682</data>
<data>2951.529,8.844</data>
<data>2953.574,8.682</data>
<data>2956.196,8.682</data>
<data>2958.118,8.52</data>
<data>2961.086,8.682</data>
<data>2962.486,8.52</data>
<data>2962.981,8.52</data>
<data>2963.114,8.52</data>
<data>2963.633,8.682</data>
<data>2964.726,8.52</data>
<data>2966.466,8.52</data>
<data>2967.776,8.52</data>
<data>2968.735,8.52</data>
<data>2970.014,8.52</data>
<data>2970.95,8.52</data>
<data>2972.11,8.52</data>
<data>2972.151,8.52</data>
<data>2972.57,8.358</data>
<data>2976.893,8.52</data>
<data>2976.893,8.52</data>
<data>2977.062,8.52</data>
<data>2977.062,8.52</data>
<data>2978.462,8.52</data>
<data>2980.725,8.52</data>
<data>2981.993,8.52</data>
<data>2983.112,8.52</data>
<data>2983.299,8.52</data>
<data>2983.496,8.52</data>
<data>2983.936,8.52</data>
<data>2984.032,8.52</data>
<data>2984.218,8.52</data>
<data>2984.426,8.682</data>
<data>2985.634,8.52</data>
<data>2986.525,8.682</data>
<data>2986.66,8.52</data>
<data>2986.792,8.682</data>
<data>2986.821,8.682</data>
<data>2987.428,8.682</data>
<data>2988.063,8.682</data>
<data>2988.561,8.682</data>
<data>2988.605,8.682</data>
<data>2988.803,8.52</data>
<data>2988.877,8.52</data>
<data>2989.254,8.52</data>
<data>2989.471,8.682</data>
<data>2989.471,8.682</data>
<data>2989.55,8.52</data>
<data>2989.564,8.52</data>
<data>2989.633,8.682</data>
<data>2989.717,8.682</data>
<data>2989.717,8.682</data>
<data>2990.087,8.682</data>
<data>2991.521,8.52</data>
<data>2992.037,8.52</data>
<data>2992.232,8.52</data>
<data>2992.253,8.52</data>
<data>2992.381,8.52</data>
<data>2992.482,8.52</data>
<data>2992.766,8.52</data>
<data>2994.208,18.091</data>
<data>2996.428,8.682</data>
<data>2998.517,8.52</data>
<data>2999.823,8.682</data>
<data>3001.143,8.52</data>
<data>3001.991,8.52</data>
<data>3002.753,8.52</data>
<data>3003.276,8.682</data>
<data>3006.882,8.52</data>
<data>3009.358,8.52</data>
<data>3011.509,8.52</data>
<data>3011.829,8.52</data>
<data>3012.09,8.52</data>
<data>3012.345,8.52</data>
<data>3012.398,8.52</data>
<data>3012.721,8.52</data>
<data>3012.77,8.52</data>
<data>3012.824,8.682</data>
<data>3012.994,8.682</data>
<data>3012.994,8.52</data>
<data>3013.023,8.52</data>
<data>3013.21,8.52</data>
<data>3013.646,8.52</data>
<data>3015.913,8.52</data>
<data>3019.49,8.682</data>
<data>3021.728,8.52</data>
<data>3022.064,8.52</data>
<data>3022.802,8.52</data>
<data>3024.823,8.52</data>
<data>3027.103,8.52</data>
<data>3029.322,8.682</data>
<data>3030.59,8.52</data>
<data>3031.235,8.52</data>
<data>3031.235,8.52</data>
<data>3031.812,8.682</data>
<data>3033.834,8.52</data>
<data>3033.999,8.52</data>
<data>3034.173,8.52</data>
<data>3034.49,8.52</data>
<data>3034.689,8.52</data>
<data>3034.767,8.52</data>
<data>3034.767,8.52</data>
<data>3034.767,8.52</data>
<data>3034.767,8.52</data>
<data>3034.775,8.52</data>
<data>3034.775,8.52</data>
<data>3034.775,8.52</data>
<data>3034.851,8.52</data>
<data>3034.851,8.52</data>
<data>3035.277,8.52</data>
<data>3035.638,8.52</data>
<data>3036.008,8.682</data>
<data>3036.475,8.682</data>
<data>3036.475,8.682</data>
<data>3036.475,8.682</data>
<data>3036.476,8.52</data>
<data>3036.476,8.52</data>
<data>3036.628,8.52</data>
<data>3036.659,8.52</data>
<data>3036.676,8.52</data>
<data>3036.676,8.52</data>
<data>3036.783,8.52</data>
<data>3036.828,8.52</data>
<data>3036.865,8.52</data>
<data>3036.918,8.52</data>
<data>3036.918,8.52</data>
<data>3036.918,8.52</data>
<data>3036.942,8.52</data>
<data>3036.969,8.52</data>
<data>3037.016,8.52</data>
<data>3037.016,8.52</data>
<data>3037.154,8.52</data>
<data>3037.157,8.52</data>
<data>3037.172,8.52</data>
<data>3037.231,8.52</data>
<data>3037.247,8.52</data>
<data>3037.29,8.52</data>
<data>3037.29,8.52</data>
<data>3037.403,8.52</data>
<data>3037.403,8.52</data>
<data>3037.403,8.52</data>
<data>3037.403,8.52</data>
<data>3037.403,8.52</data>
<data>3037.448,8.52</data>
<data>3037.472,8.52</data>
<data>3037.769,8.52</data>
<data>3038.224,8.52</data>
<data>3038.634,8.52</data>
<data>3038.71,8.52</data>
<data>3038.778,8.52</data>
<data>3038.778,8.52</data>
<data>3038.827,8.52</data>
<data>3039.533,8.52</data>
<data>3039.894,8.52</data>
<data>3040.232,8.52</data>
<data>3040.949,8.52</data>
<data>3041.114,8.52</data>
<data>3041.779,8.52</data>
<data>3042.023,8.682</data>
<data>3042.035,8.682</data>
<data>3042.078,8.682</data>
<data>3042.24,8.682</data>
<data>3042.24,8.682</data>
<data>3042.637,8.682</data>
<data>3043.371,8.52</data>
<data>3043.746,8.52</data>
<data>3044.611,8.682</data>
<data>3045.235,8.682</data>
<data>3045.795,8.682</data>
<data>3045.97,8.52</data>
<data>3046.875,8.52</data>
<data>3046.962,8.52</data>
<data>3047.212,8.682</data>
<data>3047.804,17.605</data>
<data>3048.439,8.682</data>
<data>3049.555,8.52</data>
<data>3050.586,8.52</data>
<data>3051.897,8.52</data>
<data>3053.084,8.682</data>
<data>3054.559,8.52</data>
<data>3055.6,8.682</data>
<data>3056.265,8.682</data>
<data>3057.593,8.682</data>
<data>3058.905,8.682</data>
<data>3059.974,8.682</data>
<data>3059.974,8.682</data>
<data>3059.974,8.682</data>
<data>3064.426,8.52</data>
<data>3065.648,8.682</data>
<data>3067.282,8.682</data>
<data>3069.815,8.52</data>
<data>3072.563,8.52</data>
<data>3074.663,8.52</data>
<data>3076.621,8.52</data>
<data>3077.314,8.52</data>
<data>3077.383,8.52</data>
<data>3078.028,8.52</data>
<data>3078.106,8.52</data>
<data>3078.417,8.682</data>
<data>3078.833,8.682</data>
<data>3079.976,8.52</data>
<data>3080.163,8.52</data>
<data>3082.915,8.358</data>
<data>3084.601,8.52</data>
<data>3086.106,8.52</data>
<data>3086.873,8.52</data>
<data>3087.475,8.52</data>
<data>3088.534,8.52</data>
<data>3088.579,8.52</data>
<data>3090.718,8.52</data>
<data>3091.382,8.52</data>
<data>3091.985,8.52</data>
<data>3091.985,8.52</data>
<data>3092.496,8.52</data>
<data>3093.336,8.682</data>
<data>3093.418,8.682</data>
<data>3093.547,8.52</data>
<data>3093.581,8.52</data>
<data>3094.408,8.52</data>
<data>3095.26,8.52</data>
<data>3095.957,8.52</data>
<data>3096.248,8.682</data>
<data>3096.507,8.52</data>
<data>3096.784,8.682</data>
<data>3097.162,8.682</data>
<data>3097.22,8.682</data>
<data>3097.324,8.682</data>
<data>3097.733,8.52</data>
<data>3098.304,8.52</data>
<data>3098.507,8.52</data>
<data>3098.63,8.52</data>
<data>3098.827,8.52</data>
<data>3098.827,8.52</data>
<data>3099.082,8.52</data>
<data>3099.725,8.52</data>
<data>3100.144,8.52</data>
<data>3100.316,8.682</data>
<data>3101.268,8.52</data>
<data>3102.225,8.52</data>
<data>3103.112,8.52</data>
<data>3104.089,8.682</data>
<data>3106.62,8.682</data>
<data>3107.798,8.682</data>
<data>3108.666,8.682</data>
<data>3109.356,8.682</data>
<data>3110.517,8.682</data>
<data>3111.284,8.52</data>
<data>3112.518,8.52</data>
<data>3115,8.52</data>
<data>3116.121,8.682</data>
<data>3117.683,8.682</data>
<data>3118.051,8.52</data>
<data>3119.026,8.52</data>
<data>3120.269,8.682</data>
<data>3121.252,8.682</data>
<data>3122.163,8.52</data>
<data>3123.501,8.52</data>
<data>3124.816,8.52</data>
<data>3126.898,8.52</data>
<data>3128.228,8.52</data>
<data>3129.825,8.52</data>
<data>3131.017,8.52</data>
<data>3132.944,8.52</data>
<data>3134.012,8.52</data>
<data>3135.254,8.682</data>
<data>3136.964,8.52</data>
<data>3138.328,8.52</data>
<data>3139.322,8.52</data>
<data>3139.986,8.52</data>
<data>3140.23,8.52</data>
<data>3142.232,8.52</data>
<data>3143.818,8.52</data>
<data>3145.237,8.52</data>
<data>3146.41,8.52</data>
<data>3147.636,8.52</data>
<data>3149.899,8.52</data>
<data>3151.519,8.52</data>
<data>3151.574,8.52</data>
<data>3151.862,8.52</data>
<data>3151.862,8.52</data>
<data>3151.982,8.52</data>
<data>3152.105,8.52</data>
<data>3152.371,8.52</data>
<data>3152.408,8.52</data>
<data>3152.56,8.52</data>
<data>3152.674,8.358</data>
<data>3152.808,8.52</data>
<data>3153.262,8.52</data>
<data>3153.272,8.52</data>
<data>3153.272,8.52</data>
<data>3153.284,8.52</data>
<data>3153.351,8.52</data>
<data>3153.351,8.52</data>
<data>3153.351,8.52</data>
<data>3153.351,8.52</data>
<data>3153.351,8.52</data>
<data>3153.351,8.52</data>
<data>3153.351,8.52</data>
<data>3153.435,8.52</data>
<data>3153.485,8.52</data>
<data>3153.742,8.52</data>
<data>3153.98,8.52</data>
<data>3154.026,8.52</data>
<data>3154.026,8.52</data>
<data>3154.124,8.52</data>
<data>3154.127,8.52</data>
<data>3154.135,8.52</data>
<data>3154.207,8.52</data>
<data>3154.207,8.52</data>
<data>3154.207,8.52</data>
<data>3154.207,8.52</data>
<data>3154.536,8.52</data>
<data>3154.536,8.52</data>
<data>3154.536,8.52</data>
<data>3154.536,8.52</data>
<data>3154.752,8.52</data>
<data>3154.778,8.52</data>
<data>3154.785,8.52</data>
<data>3154.906,8.52</data>
<data>3155.232,8.52</data>
<data>3156.925,8.52</data>
<data>3157.55,8.52</data>
<data>3158.54,8.52</data>
<data>3159.577,8.52</data>
<data>3160.819,8.52</data>
<data>3161.595,8.52</data>
<data>3161.669,8.52</data>
<data>3161.691,8.52</data>
<data>3161.75,8.52</data>
<data>3161.797,8.52</data>
<data>3161.84,8.52</data>
<data>3161.935,8.52</data>
<data>3162.756,8.52</data>
<data>3162.786,8.52</data>
<data>3163.044,8.52</data>
<data>3163.044,8.52</data>
<data>3163.044,8.52</data>
<data>3163.044,8.52</data>
<data>3163.044,8.52</data>
<data>3163.396,8.52</data>
<data>3163.778,8.52</data>
<data>3163.919,8.52</data>
<data>3163.989,8.52</data>
<data>3164.205,8.52</data>
<data>3164.205,8.52</data>
<data>3164.27,8.52</data>
<data>3164.27,8.52</data>
<data>3164.465,8.52</data>
<data>3164.644,8.52</data>
<data>3164.751,8.52</data>
<data>3164.751,8.52</data>
<data>3164.751,8.52</data>
<data>3164.751,8.52</data>
<data>3164.751,8.52</data>
<data>3165.451,8.52</data>
<data>3166.387,8.52</data>
<data>3166.883,8.52</data>
<data>3166.886,8.52</data>
<data>3167.305,8.52</data>
<data>3167.543,8.52</data>
<data>3167.591,8.682</data>
<data>3167.843,8.682</data>
<data>3167.843,8.682</data>
<data>3167.843,8.682</data>
<data>3167.843,8.682</data>
<data>3168.204,8.682</data>
<data>3168.204,8.682</data>
<data>3168.614,8.682</data>
<data>3169.52,8.682</data>
<data>3170.492,8.682</data>
<data>3171.666,8.52</data>
<data>3172.678,8.52</data>
<data>3174.349,8.52</data>
<data>3175.503,8.52</data>
<data>3176.349,8.682</data>
<data>3176.673,8.682</data>
<data>3176.673,8.682</data>
<data>3176.673,8.682</data>
<data>3176.935,8.682</data>
<data>3177.233,8.682</data>
<data>3177.233,8.682</data>
<data>3177.291,8.682</data>
<data>3177.307,8.682</data>
<data>3177.307,8.682</data>
<data>3177.307,8.682</data>
<data>3177.379,8.682</data>
<data>3177.379,8.682</data>
<data>3177.442,8.682</data>
<data>3177.442,8.682</data>
<data>3177.504,8.52</data>
<data>3177.565,8.52</data>
<data>3177.869,8.52</data>
<data>3178.119,8.52</data>
<data>3178.136,8.52</data>
<data>3178.25,8.52</data>
<data>3178.25,8.52</data>
<data>3178.473,8.52</data>
<data>3178.861,8.52</data>
<data>3178.861,8.52</data>
<data>3178.861,8.52</data>
<data>3179.515,8.682</data>
<data>3179.515,8.682</data>
<data>3179.515,8.682</data>
<data>3179.515,8.682</data>
<data>3179.515,8.682</data>
<data>3179.546,8.682</data>
<data>3179.965,8.682</data>
<data>3179.965,8.682</data>
<data>3179.965,8.682</data>
<data>3180.005,8.682</data>
<data>3180.005,8.682</data>
<data>3180.128,8.682</data>
<data>3180.128,8.682</data>
<data>3180.128,8.682</data>
<data>3180.128,8.52</data>
<data>3180.128,8.52</data>
<data>3180.128,8.52</data>
<data>3180.128,8.52</data>
<data>3180.128,8.52</data>
<data>3180.128,8.52</data>
<data>3180.128,8.52</data>
<data>3180.128,8.52</data>
<data>3180.128,8.52</data>
<data>3180.128,8.52</data>
<data>3180.128,8.52</data>
<data>3180.128,8.52</data>
<data>3180.182,8.52</data>
<data>3180.182,8.682</data>
<data>3180.182,8.682</data>
<data>3180.247,8.682</data>
<data>3180.247,8.682</data>
<data>3180.247,8.682</data>
<data>3180.439,8.682</data>
<data>3180.439,8.682</data>
<data>3180.542,8.682</data>
<data>3180.542,8.682</data>
<data>3180.589,8.682</data>
<data>3180.589,8.682</data>
<data>3180.734,8.682</data>
<data>3180.734,8.682</data>
<data>3180.734,8.682</data>
<data>3180.869,8.682</data>
<data>3182.666,8.682</data>
<data>3183.381,8.682</data>
<data>3184.815,8.682</data>
<data>3184.831,8.682</data>
<data>3188.25,8.52</data>
<data>3190.693,8.52</data>
<data>3193.021,8.682</data>
<data>3195.138,8.682</data>
<data>3197.146,8.52</data>
<data>3199.171,8.52</data>
<data>3201.596,8.52</data>
<data>3202.805,8.682</data>
<data>3203.836,8.52</data>
<data>3204.982,8.52</data>
<data>3205.878,8.52</data>
<data>3206.208,8.52</data>
<data>3208.801,8.844</data>
<data>3209.019,8.52</data>
<data>3209.528,17.929</data>
<data>3211.385,8.52</data>
<data>3213.939,8.52</data>
<data>3217.218,8.52</data>
<data>3217.349,8.52</data>
<data>3217.532,8.52</data>
<data>3217.649,8.52</data>
<data>3217.649,8.52</data>
<data>3217.684,8.52</data>
<data>3217.954,8.52</data>
<data>3217.954,8.52</data>
<data>3217.954,8.52</data>
<data>3217.954,8.52</data>
<data>3217.988,8.682</data>
<data>3217.988,8.52</data>
<data>3218.103,8.52</data>
<data>3218.768,8.52</data>
<data>3219.687,8.52</data>
<data>3219.687,8.52</data>
<data>3220.739,8.682</data>
<data>3220.739,8.682</data>
<data>3222.16,8.682</data>
<data>3222.16,8.682</data>
<data>3222.16,8.682</data>
<data>3224.288,8.52</data>
<data>3224.288,8.52</data>
<data>3224.328,8.52</data>
<data>3226.253,8.682</data>
<data>3226.772,8.52</data>
<data>3227.959,8.52</data>
<data>3228.52,8.52</data>
<data>3229.801,8.52</data>
<data>3230.549,17.443</data>
<data>3230.549,8.52</data>
<data>3230.796,8.52</data>
<data>3230.907,8.52</data>
<data>3230.962,8.52</data>
<data>3231.215,8.52</data>
<data>3231.215,8.52</data>
<data>3231.215,8.52</data>
<data>3231.215,8.52</data>
<data>3232.14,8.52</data>
<data>3232.14,8.52</data>
<data>3232.14,8.52</data>
<data>3232.14,8.52</data>
<data>3232.14,8.52</data>
<data>3232.14,8.52</data>
<data>3232.14,8.52</data>
<data>3232.14,8.52</data>
<data>3232.233,8.52</data>
<data>3232.404,8.52</data>
<data>3232.67,8.52</data>
<data>3233.587,8.52</data>
<data>3234.465,8.52</data>
<data>3234.631,8.682</data>
<data>3234.805,8.682</data>
<data>3235.303,8.52</data>
<data>3237.03,8.52</data>
<data>3239.528,8.52</data>
<data>3239.564,8.52</data>
<data>3240.803,8.52</data>
<data>3241.637,8.52</data>
<data>3242.745,8.52</data>
<data>3244.33,8.52</data>
<data>3245.44,8.682</data>
<data>3247.813,8.52</data>
<data>3250.397,8.682</data>
<data>3252.596,8.52</data>
<data>3254.292,8.52</data>
<data>3256.728,8.52</data>
<data>3259.294,8.52</data>
<data>3262,9.006</data>
<data>3262.944,8.844</data>
<data>3263.512,8.844</data>
<data>3264.473,8.844</data>
<data>3266.14,9.006</data>
<data>3268.887,8.844</data>
<data>3269.711,8.844</data>
<data>3270.836,9.006</data>
<data>3271.781,8.844</data>
<data>3272.647,8.844</data>
<data>3273.295,8.844</data>
<data>3273.435,9.006</data>
<data>3274.739,8.844</data>
<data>3276.019,8.844</data>
<data>3276.659,8.844</data>
<data>3276.946,8.844</data>
<data>3277.313,9.006</data>
<data>3277.453,8.844</data>
<data>3277.775,9.169</data>
<data>3278.426,9.006</data>
<data>3279.386,9.006</data>
<data>3279.957,9.169</data>
<data>3281.173,8.682</data>
<data>3281.52,8.682</data>
<data>3281.998,9.006</data>
<data>3282.386,9.006</data>
<data>3282.465,8.844</data>
<data>3282.58,9.006</data>
<data>3284.04,8.682</data>
<data>3284.04,8.682</data>
<data>3284.341,10.629</data>
<data>3284.576,9.006</data>
<data>3284.576,9.006</data>
<data>3285.205,9.169</data>
<data>3285.21,9.169</data>
<data>3286.305,9.655</data>
<data>3286.471,10.142</data>
<data>3287.906,10.304</data>
<data>3289.421,8.844</data>
<data>3289.421,8.844</data>
<data>3289.675,8.682</data>
<data>3289.816,8.682</data>
<data>3289.816,8.682</data>
<data>3290.336,9.006</data>
<data>3290.363,9.006</data>
<data>3290.504,9.006</data>
<data>3290.504,9.169</data>
<data>3290.521,9.169</data>
<data>3290.665,9.169</data>
<data>3290.665,9.169</data>
<data>3290.665,9.169</data>
<data>3290.785,9.331</data>
<data>3291.156,9.331</data>
<data>3291.254,9.655</data>
<data>3292.558,9.818</data>
<data>3292.88,10.142</data>
<data>3294.009,9.655</data>
<data>3294.526,10.142</data>
<data>3295.507,9.493</data>
<data>3296.569,8.844</data>
<data>3297.834,8.844</data>
<data>3298.274,8.844</data>
<data>3298.599,8.844</data>
<data>3299.014,8.844</data>
<data>3299.11,8.844</data>
<data>3299.279,8.844</data>
<data>3300.001,8.844</data>
<data>3300.052,8.844</data>
<data>3300.099,8.844</data>
<data>3300.292,8.844</data>
<data>3300.337,8.844</data>
<data>3300.337,8.844</data>
<data>3300.369,8.844</data>
<data>3300.534,8.844</data>
<data>3300.534,9.331</data>
<data>3300.534,9.006</data>
<data>3300.63,9.006</data>
<data>3300.63,9.006</data>
<data>3300.748,9.331</data>
<data>3301.509,8.682</data>
<data>3301.673,8.844</data>
<data>3301.869,8.682</data>
<data>3302.107,8.682</data>
<data>3302.187,8.682</data>
<data>3302.633,8.682</data>
<data>3302.633,8.682</data>
<data>3302.633,8.682</data>
<data>3302.643,8.844</data>
<data>3302.931,8.682</data>
<data>3302.931,8.682</data>
<data>3302.931,8.682</data>
<data>3302.931,8.682</data>
<data>3302.943,8.682</data>
<data>3302.998,8.682</data>
<data>3303.411,8.682</data>
<data>3303.411,8.844</data>
<data>3303.411,8.844</data>
<data>3303.411,8.844</data>
<data>3303.411,8.844</data>
<data>3303.411,8.844</data>
<data>3303.411,8.844</data>
<data>3303.411,8.844</data>
<data>3303.411,8.844</data>
<data>3303.411,8.844</data>
<data>3303.411,8.844</data>
<data>3303.411,8.844</data>
<data>3303.457,8.844</data>
<data>3303.489,8.844</data>
<data>3303.489,8.844</data>
<data>3303.644,8.682</data>
<data>3303.644,8.844</data>
<data>3303.788,8.844</data>
<data>3304.334,8.844</data>
<data>3304.334,8.844</data>
<data>3304.334,8.844</data>
<data>3304.334,8.844</data>
<data>3304.334,8.844</data>
<data>3304.334,8.844</data>
<data>3304.334,8.844</data>
<data>3304.334,8.844</data>
<data>3304.334,8.844</data>
<data>3304.357,8.844</data>
<data>3304.386,8.844</data>
<data>3304.508,8.844</data>
<data>3304.508,8.682</data>
<data>3304.553,8.682</data>
<data>3304.745,8.682</data>
<data>3304.745,8.682</data>
<data>3304.759,8.682</data>
<data>3304.759,8.844</data>
<data>3305.103,9.006</data>
<data>3305.198,9.006</data>
<data>3305.386,9.006</data>
<data>3305.625,9.169</data>
<data>3305.625,9.169</data>
<data>3305.625,9.006</data>
<data>3305.689,9.006</data>
<data>3305.747,9.006</data>
<data>3305.812,9.169</data>
<data>3305.863,9.169</data>
<data>3306.202,9.006</data>
<data>3306.202,9.006</data>
<data>3306.202,9.006</data>
<data>3306.202,9.006</data>
<data>3306.202,9.169</data>
<data>3306.202,9.169</data>
<data>3306.346,9.331</data>
<data>3306.346,9.331</data>
<data>3306.464,9.493</data>
<data>3306.579,9.006</data>
<data>3306.852,8.844</data>
<data>3306.973,9.169</data>
<data>3307.221,9.493</data>
<data>3307.433,9.98</data>
<data>3307.514,10.142</data>
<data>3307.523,10.304</data>
<data>3307.56,10.304</data>
<data>3307.592,10.304</data>
<data>3307.637,10.467</data>
<data>3307.696,10.629</data>
<data>3307.872,10.791</data>
<data>3308.056,9.98</data>
<data>3308.056,9.98</data>
<data>3308.344,9.169</data>
<data>3308.375,9.169</data>
<data>3308.577,9.169</data>
<data>3308.577,9.169</data>
<data>3308.583,9.006</data>
<data>3308.63,9.006</data>
<data>3308.69,9.006</data>
<data>3308.96,8.844</data>
<data>3308.999,8.844</data>
<data>3308.999,8.844</data>
<data>3308.999,8.682</data>
<data>3309.221,8.682</data>
<data>3309.662,8.682</data>
<data>3309.841,9.006</data>
<data>3309.841,9.006</data>
<data>3309.841,9.006</data>
<data>3309.841,9.006</data>
<data>3310.068,8.844</data>
<data>3310.406,9.169</data>
<data>3310.529,9.169</data>
<data>3310.695,9.331</data>
<data>3310.695,9.331</data>
<data>3310.695,9.331</data>
<data>3310.837,9.818</data>
<data>3310.837,9.98</data>
<data>3310.837,9.98</data>
<data>3311.008,9.98</data>
<data>3311.07,9.98</data>
<data>3311.07,9.98</data>
<data>3311.07,9.169</data>
<data>3311.197,10.629</data>
<data>3311.335,8.844</data>
<data>3311.491,8.682</data>
<data>3311.491,8.682</data>
<data>3311.529,8.682</data>
<data>3311.629,8.844</data>
<data>3311.888,8.844</data>
<data>3311.888,8.844</data>
<data>3311.888,8.844</data>
<data>3311.888,8.844</data>
<data>3311.958,8.682</data>
<data>3311.958,8.682</data>
<data>3312.064,8.844</data>
<data>3312.122,8.844</data>
<data>3312.315,9.006</data>
<data>3312.331,9.006</data>
<data>3312.331,9.006</data>
<data>3312.371,9.006</data>
<data>3312.526,9.169</data>
<data>3312.526,9.169</data>
<data>3312.526,9.006</data>
<data>3312.776,8.844</data>
<data>3313.172,9.006</data>
<data>3313.297,9.006</data>
<data>3313.432,9.169</data>
<data>3313.432,9.169</data>
<data>3313.432,9.169</data>
<data>3313.432,9.169</data>
<data>3313.432,9.169</data>
<data>3313.432,9.169</data>
<data>3313.541,9.169</data>
<data>3313.541,9.169</data>
<data>3313.541,9.169</data>
<data>3313.708,9.169</data>
<data>3313.708,9.169</data>
<data>3313.708,9.169</data>
<data>3313.711,9.169</data>
<data>3313.711,9.169</data>
<data>3313.721,9.169</data>
<data>3313.721,9.169</data>
<data>3313.805,9.169</data>
<data>3313.808,9.169</data>
<data>3313.822,9.169</data>
<data>3313.839,9.169</data>
<data>3313.855,9.169</data>
<data>3313.855,9.169</data>
<data>3313.879,9.169</data>
<data>3313.902,9.169</data>
<data>3313.902,9.169</data>
<data>3313.902,9.169</data>
<data>3314.008,9.169</data>
<data>3314.056,9.169</data>
<data>3314.237,9.169</data>
<data>3314.437,9.169</data>
<data>3314.437,9.655</data>
<data>3315.369,9.818</data>
<data>3315.438,9.493</data>
<data>3315.639,8.844</data>
<data>3315.79,9.006</data>
<data>3316.169,9.169</data>
<data>3316.269,9.169</data>
<data>3316.298,9.169</data>
<data>3316.363,9.169</data>
<data>3316.368,9.006</data>
<data>3316.584,9.006</data>
<data>3316.641,9.006</data>
<data>3316.641,9.006</data>
<data>3316.767,9.006</data>
<data>3316.772,9.006</data>
<data>3316.808,9.006</data>
<data>3316.808,9.006</data>
<data>3316.837,9.006</data>
<data>3316.974,9.006</data>
<data>3316.974,9.006</data>
<data>3317.028,9.006</data>
<data>3317.028,9.006</data>
<data>3317.113,9.006</data>
<data>3317.113,9.006</data>
<data>3317.153,9.006</data>
<data>3317.197,9.006</data>
<data>3317.197,9.006</data>
<data>3317.197,9.006</data>
<data>3317.197,9.006</data>
<data>3317.197,9.006</data>
<data>3317.197,9.006</data>
<data>3317.197,9.006</data>
<data>3317.241,9.006</data>
<data>3317.241,9.006</data>
<data>3317.241,9.006</data>
<data>3317.241,9.006</data>
<data>3317.33,9.006</data>
<data>3317.33,9.006</data>
<data>3317.33,9.006</data>
<data>3317.33,9.006</data>
<data>3317.33,9.006</data>
<data>3317.33,9.006</data>
<data>3317.33,9.006</data>
<data>3317.33,9.006</data>
<data>3317.33,9.006</data>
<data>3317.33,9.006</data>
<data>3317.33,9.006</data>
<data>3317.33,9.006</data>
<data>3317.33,9.006</data>
<data>3317.33,9.006</data>
<data>3317.33,9.006</data>
<data>3317.33,9.006</data>
<data>3317.33,9.006</data>
<data>3317.33,9.006</data>
<data>3317.33,9.006</data>
<data>3317.33,9.006</data>
<data>3317.33,9.006</data>
<data>3317.33,9.006</data>
<data>3317.33,9.006</data>
<data>3317.33,9.006</data>
<data>3317.342,9.006</data>
<data>3317.342,9.006</data>
<data>3317.342,9.006</data>
<data>3317.387,9.006</data>
<data>3317.387,9.006</data>
<data>3317.387,9.006</data>
<data>3317.387,9.006</data>
<data>3317.387,9.006</data>
<data>3317.387,9.006</data>
<data>3317.387,9.006</data>
<data>3317.387,9.006</data>
<data>3317.387,9.006</data>
<data>3317.387,9.006</data>
<data>3317.387,9.006</data>
<data>3317.427,9.006</data>
<data>3317.447,9.006</data>
<data>3317.447,9.006</data>
<data>3317.447,9.006</data>
<data>3317.484,9.006</data>
<data>3317.484,9.006</data>
<data>3317.484,9.006</data>
<data>3317.484,9.006</data>
<data>3317.484,9.006</data>
<data>3317.484,9.006</data>
<data>3317.484,9.006</data>
<data>3317.484,9.006</data>
<data>3317.557,9.006</data>
<data>3317.595,9.006</data>
<data>3317.744,9.006</data>
<data>3317.744,9.006</data>
<data>3317.744,9.006</data>
<data>3317.744,9.006</data>
<data>3317.744,9.006</data>
<data>3317.744,9.006</data>
<data>3317.744,9.006</data>
<data>3317.805,9.006</data>
</logData>
    <commonData>
      <nameSource>SC001</nameSource>
      <dTimStamp>2007-06-11T14:24:48.6160000+02:00</dTimStamp>
      <dTimCreation>2007-06-07T11:22:14.7030000+02:00</dTimCreation>
      <dTimLastChange>2007-06-08T14:42:19.9210000+02:00</dTimLastChange>
      <itemState>Actual</itemState>
    </commonData>
  </log>
</logs>
