<?xml version="1.0" encoding="UTF-8"?>
	<!-- POSC License Agreement
	This file is distributed under the POSC License Agreement at
	http://www.posc.org/about/license.shtml.
	Use of this file constitutes agreement with the POSC License Agreement.
	-->
<logs 
	xmlns="http://www.witsml.org/schemas/120" 
	xmlns:xsi="http://www.w3.org/2001/XMLSchema-instance" 
	xsi:schemaLocation="http://www.witsml.org/schemas/120 
	http://www.witsml.org/schemas/120/obj_log.xsd" 
	version="1.2.0">
  <log uidWell="Well123" uidWellbore="6KFSJ18" uidLog="170KKJH14" uidSource="Server1">
    <nameWell>DemoWell2</nameWell>
    <nameWellbore>Wellbore3</nameWellbore>
    <nameLog>MPRALFLS</nameLog>
    <logHeader>
      <serviceCompany>ServiceCompany</serviceCompany>
      <runNumber>10</runNumber>
      <creationDate>2007-02-17T11:29:15.0000000+01:00</creationDate>
      <indexType>Depth</indexType>
      <startIndex>2943.271</startIndex>
      <endIndex>3328.335</endIndex>
      <direction>Increasing</direction>
      <indexCurve>Depth</indexCurve>
      <stepIncrement>0</stepIncrement>
      <indexUnits>m</indexUnits>
      <nullValue>-999.25</nullValue>
      <uomNamingSystem>RP66</uomNamingSystem>
      <logCurveInfo>
        <mnemonic>Depth</mnemonic>
        <unit>m</unit>
        <startIndex>2943.271</startIndex>
        <endIndex>3328.335</endIndex>
        <columnIndex>1</columnIndex>
        <curveDescription>The mnemonic of the index curve</curveDescription>
        <sensorOffset>0</sensorOffset>
        <traceState>Raw</traceState>
        <typeLogData>Double</typeLogData>
      </logCurveInfo>
      <logCurveInfo>
        <mnemonic>RACELX</mnemonic>
        <unit>ohm.m</unit>
        <mnemAlias>mresC</mnemAlias>
        <nullValue>-999.25</nullValue>
        <startIndex>2943.271</startIndex>
        <endIndex>3328.335</endIndex>
        <columnIndex>2</columnIndex>
        <curveDescription>Resistivity Attenuation - Corrected - CRIM - 400kHz</curveDescription>
        <typeLogData>Double</typeLogData>
      </logCurveInfo>
    </logHeader>
<logData>
<data>2943.271,0.967</data>
<data>2943.271,0.207</data>
<data>2944.284,0.158</data>
<data>2944.284,6.868</data>
<data>2944.284,8.064</data>
<data>2944.284,7.073</data>
<data>2944.284,7.06</data>
<data>2944.284,6.868</data>
<data>2944.284,8.064</data>
<data>2944.284,7.073</data>
<data>2944.284,7.06</data>
<data>2944.284,6.236</data>
<data>2944.284,7.719</data>
<data>2944.284,6.118</data>
<data>2944.284,6.648</data>
<data>2944.284,9.02</data>
<data>2945.159,7.086</data>
<data>2945.205,6.015</data>
<data>2948.208,5.009</data>
<data>2949.217,5.733</data>
<data>2949.217,5.733</data>
<data>2949.685,5.554</data>
<data>2950.464,0.496</data>
<data>2950.464,0.289</data>
<data>2950.674,0.209</data>
<data>2950.823,0.209</data>
<data>2952.182,5.184</data>
<data>2952.662,6.045</data>
<data>2953.255,7.51</data>
<data>2953.384,7.086</data>
<data>2953.462,7.232</data>
<data>2953.47,7.64</data>
<data>2953.745,6.696</data>
<data>2953.799,6.577</data>
<data>2954.45,6.192</data>
<data>2954.524,6.269</data>
<data>2954.669,6.325</data>
<data>2955.489,4.546</data>
<data>2955.648,4.49</data>
<data>2956.735,6.056</data>
<data>2957.06,6.944</data>
<data>2957.766,6.369</data>
<data>2957.922,6.381</data>
<data>2958.375,5.386</data>
<data>2958.811,4.58</data>
<data>2959.365,4.018</data>
<data>2959.856,4.34</data>
<data>2961.288,3.745</data>
<data>2961.544,3.979</data>
<data>2962.557,3.643</data>
<data>2963.212,3.054</data>
<data>2964.561,2.842</data>
<data>2965.723,2.725</data>
<data>2967.207,2.667</data>
<data>2968.052,2.508</data>
<data>2970.31,2.38</data>
<data>2971.139,2.725</data>
<data>2972.069,2.516</data>
<data>2973.35,2.434</data>
<data>2973.468,2.439</data>
<data>2973.547,2.418</data>
<data>2973.599,2.437</data>
<data>2973.805,2.508</data>
<data>2973.938,2.497</data>
<data>2974.23,2.577</data>
<data>2974.7,2.657</data>
<data>2975.846,2.589</data>
<data>2976.366,2.675</data>
<data>2977.396,2.74</data>
<data>2977.788,2.759</data>
<data>2978.498,2.86</data>
<data>2978.912,2.751</data>
<data>2979.84,2.712</data>
<data>2980.115,2.696</data>
<data>2981.166,2.521</data>
<data>2981.301,2.558</data>
<data>2981.634,2.679</data>
<data>2982.256,2.503</data>
<data>2982.901,2.549</data>
<data>2983.696,2.471</data>
<data>2987.002,2.339</data>
<data>2987.002,2.339</data>
<data>2987.277,2.297</data>
<data>2987.423,2.317</data>
<data>2987.423,2.317</data>
<data>2987.423,2.354</data>
<data>2987.423,2.317</data>
<data>2987.423,2.354</data>
<data>2987.764,2.309</data>
<data>2988.237,2.456</data>
<data>2989.481,2.536</data>
<data>2990.83,2.604</data>
<data>2992.132,2.512</data>
<data>2992.447,2.549</data>
<data>2992.646,2.556</data>
<data>2993.362,2.618</data>
<data>2993.642,2.601</data>
<data>2993.768,2.602</data>
<data>2993.829,2.568</data>
<data>2993.979,2.558</data>
<data>2994.233,2.583</data>
<data>2994.378,2.56</data>
<data>2994.466,2.574</data>
<data>2994.515,2.575</data>
<data>2994.585,2.564</data>
<data>2994.616,2.566</data>
<data>2994.835,2.62</data>
<data>2995.014,2.851</data>
<data>2995.797,2.951</data>
<data>2996.231,2.917</data>
<data>2996.387,2.788</data>
<data>2996.62,2.719</data>
<data>2997.083,2.71</data>
<data>2997.1,2.7</data>
<data>2997.19,2.717</data>
<data>2997.242,2.746</data>
<data>2997.322,2.799</data>
<data>2997.879,2.881</data>
<data>2997.879,2.853</data>
<data>2998.267,2.749</data>
<data>2998.515,2.704</data>
<data>2998.593,2.708</data>
<data>2998.839,2.696</data>
<data>2999.106,2.673</data>
<data>2999.106,2.675</data>
<data>2999.184,2.683</data>
<data>2999.333,2.71</data>
<data>2999.333,2.683</data>
<data>2999.407,2.698</data>
<data>2999.437,2.698</data>
<data>2999.463,2.725</data>
<data>2999.806,2.71</data>
<data>2999.934,2.692</data>
<data>3000.001,2.687</data>
<data>3000.001,2.687</data>
<data>3000.001,2.685</data>
<data>3000.08,2.69</data>
<data>3000.08,2.7</data>
<data>3000.094,2.734</data>
<data>3000.163,2.755</data>
<data>3000.163,2.79</data>
<data>3000.163,2.77</data>
<data>3000.183,2.777</data>
<data>3000.247,2.764</data>
<data>3000.247,2.749</data>
<data>3000.273,2.91</data>
<data>3001.814,3.268</data>
<data>3001.855,3.295</data>
<data>3002.123,3.313</data>
<data>3002.204,3.31</data>
<data>3002.691,3.362</data>
<data>3002.757,3.335</data>
<data>3002.765,3.362</data>
<data>3002.783,3.391</data>
<data>3002.783,3.42</data>
<data>3002.796,3.443</data>
<data>3002.993,3.482</data>
<data>3003.012,3.509</data>
<data>3003.107,3.516</data>
<data>3003.108,3.523</data>
<data>3003.181,3.187</data>
<data>3003.976,2.649</data>
<data>3004.367,2.496</data>
<data>3005.611,2.441</data>
<data>3006.455,2.545</data>
<data>3007.464,2.681</data>
<data>3008.166,2.516</data>
<data>3008.956,2.254</data>
<data>3009.263,2.207</data>
<data>3010.097,1.948</data>
<data>3010.097,1.918</data>
<data>3010.904,2.229</data>
<data>3011.377,2.102</data>
<data>3011.912,2.084</data>
<data>3012.18,2.083</data>
<data>3012.705,2.061</data>
<data>3013.151,2.097</data>
<data>3013.447,2.066</data>
<data>3014.346,1.874</data>
<data>3016.363,1.849</data>
<data>3016.637,1.818</data>
<data>3017.97,1.892</data>
<data>3019.084,1.894</data>
<data>3020.533,1.904</data>
<data>3021.679,1.922</data>
<data>3022.273,1.943</data>
<data>3022.341,1.916</data>
<data>3022.359,1.911</data>
<data>3022.389,1.914</data>
<data>3022.749,1.907</data>
<data>3022.825,1.918</data>
<data>3022.907,1.905</data>
<data>3022.926,1.878</data>
<data>3022.991,1.864</data>
<data>3023.231,1.869</data>
<data>3023.251,1.84</data>
<data>3023.3,1.846</data>
<data>3023.3,1.828</data>
<data>3023.317,1.831</data>
<data>3023.524,1.831</data>
<data>3023.524,1.839</data>
<data>3023.524,1.834</data>
<data>3023.524,1.839</data>
<data>3023.524,1.832</data>
<data>3023.524,1.83</data>
<data>3023.553,1.856</data>
<data>3023.553,1.852</data>
<data>3023.558,1.872</data>
<data>3024.526,1.831</data>
<data>3025.042,1.839</data>
<data>3028.015,1.832</data>
<data>3028.883,2.158</data>
<data>3030.971,2.198</data>
<data>3031.543,1.984</data>
<data>3031.829,1.958</data>
<data>3032.321,1.903</data>
<data>3032.475,1.909</data>
<data>3032.593,1.835</data>
<data>3033.975,1.871</data>
<data>3034.656,1.844</data>
<data>3035.802,1.856</data>
<data>3036.778,1.884</data>
<data>3038.173,1.852</data>
<data>3039.001,1.758</data>
<data>3040.085,1.742</data>
<data>3040.478,1.874</data>
<data>3041.35,1.967</data>
<data>3041.657,1.939</data>
<data>3041.765,1.892</data>
<data>3041.765,1.884</data>
<data>3042.836,1.863</data>
<data>3043.515,1.932</data>
<data>3044.392,1.93</data>
<data>3044.529,1.905</data>
<data>3044.529,1.906</data>
<data>3044.602,1.903</data>
<data>3044.807,1.904</data>
<data>3044.873,1.905</data>
<data>3045.04,1.926</data>
<data>3045.04,1.921</data>
<data>3045.219,1.925</data>
<data>3045.297,1.918</data>
<data>3045.297,1.93</data>
<data>3045.297,1.906</data>
<data>3045.297,1.933</data>
<data>3045.297,1.915</data>
<data>3045.297,1.95</data>
<data>3045.297,1.902</data>
<data>3045.297,1.932</data>
<data>3045.297,1.996</data>
<data>3045.297,2.007</data>
<data>3045.305,1.956</data>
<data>3045.305,2.004</data>
<data>3045.305,1.864</data>
<data>3045.305,1.958</data>
<data>3045.305,1.987</data>
<data>3045.381,1.933</data>
<data>3045.381,2.027</data>
<data>3045.381,1.892</data>
<data>3045.807,2.056</data>
<data>3045.807,1.99</data>
<data>3046.256,1.981</data>
<data>3046.358,2.007</data>
<data>3046.727,1.945</data>
<data>3047.005,1.978</data>
<data>3047.005,1.97</data>
<data>3047.005,1.977</data>
<data>3047.005,1.978</data>
<data>3047.005,1.971</data>
<data>3047.005,1.981</data>
<data>3047.006,1.977</data>
<data>3047.006,1.984</data>
<data>3047.006,1.995</data>
<data>3047.006,1.99</data>
<data>3047.098,2.005</data>
<data>3047.189,1.957</data>
<data>3047.189,2.032</data>
<data>3047.206,1.969</data>
<data>3047.206,2.027</data>
<data>3047.206,1.971</data>
<data>3047.206,2.07</data>
<data>3047.206,2.085</data>
<data>3047.206,2.024</data>
<data>3047.313,1.957</data>
<data>3047.313,1.909</data>
<data>3047.395,2.076</data>
<data>3047.395,2.053</data>
<data>3047.395,2.092</data>
<data>3047.448,1.949</data>
<data>3047.448,2.009</data>
<data>3047.448,2.136</data>
<data>3047.448,2.155</data>
<data>3047.448,1.989</data>
<data>3047.448,1.969</data>
<data>3047.472,1.974</data>
<data>3047.472,2.108</data>
<data>3047.472,1.923</data>
<data>3047.472,2.007</data>
<data>3047.499,1.937</data>
<data>3047.499,1.969</data>
<data>3047.546,1.865</data>
<data>3047.546,1.934</data>
<data>3047.546,1.901</data>
<data>3047.546,2.047</data>
<data>3047.56,1.949</data>
<data>3047.687,1.934</data>
<data>3047.687,2.01</data>
<data>3047.702,2.024</data>
<data>3047.702,1.958</data>
<data>3047.702,2.002</data>
<data>3047.702,1.996</data>
<data>3047.777,2.117</data>
<data>3047.777,2.163</data>
<data>3047.777,2.214</data>
<data>3047.82,1.936</data>
<data>3047.82,2.014</data>
<data>3047.82,2.18</data>
<data>3047.82,2.011</data>
<data>3047.933,1.942</data>
<data>3047.933,1.967</data>
<data>3047.933,1.977</data>
<data>3047.933,2.029</data>
<data>3047.933,2.035</data>
<data>3047.933,2.1</data>
<data>3047.933,2.18</data>
<data>3047.933,2.187</data>
<data>3047.933,2.227</data>
<data>3047.933,2.013</data>
<data>3047.978,2.061</data>
<data>3047.978,2.097</data>
<data>3048.002,2.026</data>
<data>3048.018,2.147</data>
<data>3048.407,2.053</data>
<data>3048.544,2.027</data>
<data>3048.815,2.033</data>
<data>3048.829,2.052</data>
<data>3049.221,2.045</data>
<data>3049.24,2.021</data>
<data>3049.24,2.057</data>
<data>3049.308,2.003</data>
<data>3049.308,2.031</data>
<data>3049.308,2.035</data>
<data>3049.308,2.033</data>
<data>3049.357,2.051</data>
<data>3049.366,2.065</data>
<data>3049.532,2.051</data>
<data>3049.583,2.149</data>
<data>3049.65,1.974</data>
<data>3050.063,1.915</data>
<data>3050.375,1.977</data>
<data>3050.864,1.923</data>
<data>3051.003,1.895</data>
<data>3051.482,2.005</data>
<data>3051.521,1.846</data>
<data>3051.97,1.977</data>
<data>3052.016,1.923</data>
<data>3052.628,1.874</data>
<data>3052.75,1.931</data>
<data>3052.751,1.962</data>
<data>3052.77,1.957</data>
<data>3052.77,1.958</data>
<data>3052.911,1.941</data>
<data>3053.167,2.005</data>
<data>3053.432,0.376</data>
<data>3053.651,2.162</data>
<data>3053.673,2.106</data>
<data>3054.069,2.088</data>
<data>3054.488,2.021</data>
<data>3054.75,2.05</data>
<data>3055.307,2.036</data>
<data>3055.378,2.074</data>
<data>3055.805,2.116</data>
<data>3056.213,2.052</data>
<data>3056.717,2.121</data>
<data>3057.396,2.029</data>
<data>3057.405,2.045</data>
<data>3057.413,1.979</data>
<data>3057.493,1.98</data>
<data>3057.634,1.99</data>
<data>3057.944,1.971</data>
<data>3057.955,2.066</data>
<data>3058.327,1.992</data>
<data>3058.596,1.978</data>
<data>3059.302,2.015</data>
<data>3059.429,1.989</data>
<data>3060.555,1.78</data>
<data>3060.805,1.857</data>
<data>3061.283,2.242</data>
<data>3062.064,2.16</data>
<data>3062.723,2.266</data>
<data>3063.31,2.045</data>
<data>3064.078,2.255</data>
<data>3064.296,1.956</data>
<data>3065.408,1.816</data>
<data>3065.884,1.786</data>
<data>3066.408,1.9</data>
<data>3066.625,2.301</data>
<data>3066.958,2.315</data>
<data>3067.321,2.373</data>
<data>3068.365,2.608</data>
<data>3069.037,2.91</data>
<data>3070.161,0.14</data>
<data>3070.441,2.828</data>
<data>3070.462,2.738</data>
<data>3070.78,0.281</data>
<data>3071.088,2.84</data>
<data>3071.402,2.917</data>
<data>3073.98,2.328</data>
<data>3073.98,2.328</data>
<data>3074.64,2.328</data>
<data>3075.332,2.226</data>
<data>3075.862,2.268</data>
<data>3076.458,2.396</data>
<data>3076.967,2.513</data>
<data>3078.503,2.493</data>
<data>3079.399,2.606</data>
<data>3081.324,2.547</data>
<data>3082.195,2.53</data>
<data>3083.697,2.636</data>
<data>3084.457,2.748</data>
<data>3085.654,3.729</data>
<data>3086.419,3.123</data>
<data>3087.54,2.744</data>
<data>3087.724,2.857</data>
<data>3087.913,2.772</data>
<data>3087.913,2.716</data>
<data>3087.913,2.812</data>
<data>3087.913,3.505</data>
<data>3088.404,2.867</data>
<data>3088.408,2.878</data>
<data>3088.558,2.89</data>
<data>3088.558,2.888</data>
<data>3088.819,2.914</data>
<data>3088.819,2.919</data>
<data>3088.89,3.192</data>
<data>3089.168,3.153</data>
<data>3089.186,3.139</data>
<data>3089.45,3.107</data>
<data>3089.616,3.072</data>
<data>3089.725,2.965</data>
<data>3090.745,3.699</data>
<data>3091.245,3.636</data>
<data>3092.142,2.805</data>
<data>3092.773,2.982</data>
<data>3093.704,2.916</data>
<data>3094.473,3.3</data>
<data>3095.466,3.603</data>
<data>3096.252,3.137</data>
<data>3096.704,3.051</data>
<data>3097.071,3.062</data>
<data>3097.806,3.109</data>
<data>3098.42,3.046</data>
<data>3099.458,3</data>
<data>3100.045,2.943</data>
<data>3101.733,2.706</data>
<data>3101.91,2.752</data>
<data>3102.038,2.695</data>
<data>3102.515,2.697</data>
<data>3102.515,2.725</data>
<data>3102.515,2.706</data>
<data>3102.645,2.83</data>
<data>3102.89,2.819</data>
<data>3103.07,2.768</data>
<data>3103.741,2.867</data>
<data>3103.871,2.848</data>
<data>3103.88,2.874</data>
<data>3104.065,2.902</data>
<data>3104.077,2.876</data>
<data>3104.676,2.81</data>
<data>3104.908,2.781</data>
<data>3104.938,0.827</data>
<data>3105.685,2.67</data>
<data>3105.685,2.677</data>
<data>3105.975,2.56</data>
<data>3106.413,2.508</data>
<data>3106.487,2.497</data>
<data>3106.678,2.481</data>
<data>3106.778,2.47</data>
<data>3107.037,2.453</data>
<data>3107.105,2.486</data>
<data>3107.314,2.522</data>
<data>3107.692,2.526</data>
<data>3107.692,2.511</data>
<data>3107.75,2.497</data>
<data>3107.75,2.49</data>
<data>3107.75,2.486</data>
<data>3107.75,2.484</data>
<data>3107.952,2.432</data>
<data>3108.128,2.458</data>
<data>3108.606,2.444</data>
<data>3108.662,2.453</data>
<data>3108.989,2.456</data>
<data>3108.989,2.439</data>
<data>3109.127,2.513</data>
<data>3109.127,2.493</data>
<data>3109.322,2.51</data>
<data>3109.357,2.495</data>
<data>3109.357,2.486</data>
<data>3109.357,2.495</data>
<data>3109.357,2.513</data>
<data>3109.362,2.521</data>
<data>3109.837,2.502</data>
<data>3110.225,2.484</data>
<data>3110.493,2.526</data>
<data>3110.55,2.511</data>
<data>3110.804,2.439</data>
<data>3110.804,2.447</data>
<data>3110.875,2.467</data>
<data>3111.459,2.481</data>
<data>3112.088,2.44</data>
<data>3112.411,2.481</data>
<data>3112.935,2.458</data>
<data>3113.323,2.34</data>
<data>3113.868,2.355</data>
<data>3114.142,2.296</data>
<data>3114.162,2.276</data>
<data>3116.614,2.508</data>
<data>3116.614,2.508</data>
<data>3116.946,2.677</data>
<data>3116.946,2.677</data>
<data>3117.29,3.126</data>
<data>3117.957,3.164</data>
<data>3118.62,2.565</data>
<data>3118.793,2.366</data>
<data>3119.311,2.289</data>
<data>3119.366,2.279</data>
<data>3120.345,2.352</data>
<data>3120.774,2.293</data>
<data>3121.21,2.26</data>
<data>3121.421,2.307</data>
<data>3122.233,2.109</data>
<data>3122.483,2.142</data>
<data>3123.654,2.094</data>
<data>3123.964,2.11</data>
<data>3124.421,2.122</data>
<data>3124.421,2.003</data>
<data>3124.683,2.046</data>
<data>3124.88,2.021</data>
<data>3126.022,1.986</data>
<data>3126.47,2.106</data>
<data>3127.005,2.309</data>
<data>3127.517,2.479</data>
<data>3127.586,2.65</data>
<data>3128.485,2.632</data>
<data>3129.054,2.289</data>
<data>3130.083,2.164</data>
<data>3131.15,2.192</data>
<data>3131.299,2.191</data>
<data>3132.018,2.198</data>
<data>3132.329,2.317</data>
<data>3132.725,2.252</data>
<data>3133.256,2.218</data>
<data>3134.382,2.266</data>
<data>3134.841,2.145</data>
<data>3136.147,2.246</data>
<data>3136.914,2.592</data>
<data>3138.005,2.776</data>
<data>3138.719,2.596</data>
<data>3139.154,2.307</data>
<data>3139.827,2.374</data>
<data>3140.536,2.608</data>
<data>3141.15,2.673</data>
<data>3142.189,2.467</data>
<data>3142.998,2.517</data>
<data>3143.692,2.439</data>
<data>3144.07,2.592</data>
<data>3144.986,2.608</data>
<data>3145.743,2.77</data>
<data>3146.274,2.794</data>
<data>3146.76,2.596</data>
<data>3147.792,2.63</data>
<data>3148.275,2.628</data>
<data>3149.177,2.504</data>
<data>3149.361,2.467</data>
<data>3150.083,2.528</data>
<data>3150.448,2.567</data>
<data>3150.516,2.477</data>
<data>3150.658,2.547</data>
<data>3151.485,2.729</data>
<data>3152.07,2.731</data>
<data>3153.066,2.618</data>
<data>3153.773,2.583</data>
<data>3154.587,2.71</data>
<data>3155.263,2.729</data>
<data>3156.343,2.588</data>
<data>3156.744,2.622</data>
<data>3157.08,2.733</data>
<data>3157.737,2.693</data>
<data>3158.48,2.606</data>
<data>3158.852,2.695</data>
<data>3158.867,2.681</data>
<data>3160.397,2.96</data>
<data>3160.397,2.731</data>
<data>3161.894,2.85</data>
<data>3162.049,2.837</data>
<data>3162.049,2.735</data>
<data>3162.049,2.697</data>
<data>3162.104,2.714</data>
<data>3162.183,2.722</data>
<data>3162.392,2.685</data>
<data>3162.392,2.828</data>
<data>3162.512,2.768</data>
<data>3162.512,2.695</data>
<data>3162.549,2.699</data>
<data>3162.549,2.656</data>
<data>3162.635,2.677</data>
<data>3162.901,2.668</data>
<data>3162.938,2.65</data>
<data>3162.938,2.65</data>
<data>3162.938,2.666</data>
<data>3162.938,2.646</data>
<data>3163.204,2.646</data>
<data>3163.204,2.683</data>
<data>3163.204,2.636</data>
<data>3163.204,2.624</data>
<data>3163.531,2.701</data>
<data>3163.792,2.622</data>
<data>3163.792,2.606</data>
<data>3163.802,2.642</data>
<data>3163.802,2.634</data>
<data>3163.802,2.624</data>
<data>3163.814,2.614</data>
<data>3163.814,2.646</data>
<data>3163.824,2.602</data>
<data>3163.881,2.634</data>
<data>3163.881,2.59</data>
<data>3163.881,2.577</data>
<data>3163.881,2.602</data>
<data>3163.881,2.646</data>
<data>3163.881,2.604</data>
<data>3163.881,2.569</data>
<data>3163.881,2.594</data>
<data>3163.881,2.539</data>
<data>3163.881,2.573</data>
<data>3163.881,2.55</data>
<data>3163.881,2.552</data>
<data>3163.881,2.56</data>
<data>3163.896,2.569</data>
<data>3164.015,2.583</data>
<data>3164.015,2.573</data>
<data>3164.021,2.63</data>
<data>3164.021,2.624</data>
<data>3164.205,2.528</data>
<data>3164.205,2.565</data>
<data>3164.272,2.569</data>
<data>3164.509,2.562</data>
<data>3164.51,2.534</data>
<data>3164.556,2.552</data>
<data>3164.556,2.554</data>
<data>3164.556,2.548</data>
<data>3164.654,2.554</data>
<data>3164.654,2.53</data>
<data>3164.654,2.545</data>
<data>3164.654,2.541</data>
<data>3164.657,2.403</data>
<data>3164.665,2.545</data>
<data>3164.737,2.528</data>
<data>3164.737,2.528</data>
<data>3164.737,2.534</data>
<data>3164.737,2.517</data>
<data>3164.737,2.513</data>
<data>3164.737,2.524</data>
<data>3164.737,2.499</data>
<data>3164.737,2.608</data>
<data>3164.737,2.526</data>
<data>3164.737,2.492</data>
<data>3165.066,2.528</data>
<data>3165.066,2.475</data>
<data>3165.066,2.504</data>
<data>3165.066,2.495</data>
<data>3165.066,2.511</data>
<data>3165.303,2.483</data>
<data>3165.308,2.532</data>
<data>3165.308,2.46</data>
<data>3165.315,2.49</data>
<data>3165.315,2.481</data>
<data>3165.315,2.51</data>
<data>3165.436,2.483</data>
<data>3165.744,2.528</data>
<data>3166.533,2.481</data>
<data>3167.09,2.556</data>
<data>3167.538,2.577</data>
<data>3167.771,2.456</data>
<data>3168.52,2.577</data>
<data>3169.543,2.948</data>
<data>3169.938,3.665</data>
<data>3170.098,4.283</data>
<data>3170.584,3.752</data>
<data>3171.686,5.267</data>
<data>3171.843,5.298</data>
<data>3172.125,4.954</data>
<data>3172.199,5.434</data>
<data>3172.221,4.887</data>
<data>3172.245,5.369</data>
<data>3172.28,5.205</data>
<data>3172.28,5.345</data>
<data>3172.327,5.095</data>
<data>3172.327,5.641</data>
<data>3172.327,5.329</data>
<data>3172.465,5.243</data>
<data>3172.465,5.243</data>
<data>3172.465,5.476</data>
<data>3173.208,5.236</data>
<data>3173.286,5.298</data>
<data>3173.316,5.75</data>
<data>3173.316,5.236</data>
<data>3173.387,5.321</data>
<data>3173.387,5.205</data>
<data>3173.574,5.361</data>
<data>3173.574,5.329</data>
<data>3173.574,5.329</data>
<data>3173.574,5.205</data>
<data>3173.574,5.443</data>
<data>3173.574,5.426</data>
<data>3173.574,5.329</data>
<data>3173.574,5.337</data>
<data>3173.574,5.544</data>
<data>3173.672,5.002</data>
<data>3173.672,4.954</data>
<data>3173.859,5.102</data>
<data>3173.935,4.413</data>
<data>3174.156,4.556</data>
<data>3174.231,4.044</data>
<data>3174.496,3.91</data>
<data>3174.519,4.517</data>
<data>3174.519,4.528</data>
<data>3174.531,4.562</data>
<data>3174.735,4.602</data>
<data>3174.735,4.784</data>
<data>3174.735,4.467</data>
<data>3174.8,4.573</data>
<data>3174.8,4.632</data>
<data>3174.8,4.539</data>
<data>3174.8,4.456</data>
<data>3174.935,3.55</data>
<data>3174.98,3.303</data>
<data>3174.995,3.603</data>
<data>3175.025,3.288</data>
<data>3175.098,4.391</data>
<data>3175.281,4.461</data>
<data>3175.281,4.36</data>
<data>3175.281,4.298</data>
<data>3175.281,4.248</data>
<data>3175.281,4.268</data>
<data>3175.281,4.218</data>
<data>3175.281,4.268</data>
<data>3175.281,4.09</data>
<data>3175.281,4.189</data>
<data>3175.494,3.15</data>
<data>3175.981,3.21</data>
<data>3176.052,3.064</data>
<data>3176.202,2.992</data>
<data>3177.088,2.716</data>
<data>3177.187,2.679</data>
<data>3177.416,2.729</data>
<data>3177.416,2.718</data>
<data>3177.416,2.626</data>
<data>3177.416,2.716</data>
<data>3178.073,2.748</data>
<data>3178.073,2.704</data>
<data>3178.073,2.701</data>
<data>3178.121,2.72</data>
<data>3178.121,2.695</data>
<data>3178.121,2.628</data>
<data>3178.373,2.679</data>
<data>3178.373,2.708</data>
<data>3178.373,2.67</data>
<data>3178.373,2.697</data>
<data>3178.373,2.668</data>
<data>3178.373,2.67</data>
<data>3178.498,2.654</data>
<data>3178.515,2.583</data>
<data>3178.734,2.65</data>
<data>3178.734,2.689</data>
<data>3178.734,2.668</data>
<data>3178.734,2.704</data>
<data>3179.426,2.654</data>
<data>3179.969,2.61</data>
<data>3180.522,2.785</data>
<data>3180.522,2.716</data>
<data>3181.303,2.687</data>
<data>3181.842,2.99</data>
<data>3182.597,2.816</data>
<data>3182.597,2.646</data>
<data>3183.757,2.472</data>
<data>3184.155,2.252</data>
<data>3185.008,2.403</data>
<data>3185.679,2.616</data>
<data>3186.433,2.77</data>
<data>3186.513,2.853</data>
<data>3187.203,2.821</data>
<data>3187.203,2.772</data>
<data>3187.203,2.774</data>
<data>3187.203,2.689</data>
<data>3187.203,2.919</data>
<data>3187.203,2.794</data>
<data>3187.314,2.85</data>
<data>3187.465,2.862</data>
<data>3187.508,2.902</data>
<data>3187.763,2.693</data>
<data>3187.763,2.735</data>
<data>3187.763,2.816</data>
<data>3187.763,2.841</data>
<data>3187.821,2.759</data>
<data>3187.837,2.733</data>
<data>3187.837,2.885</data>
<data>3187.837,2.832</data>
<data>3187.837,2.768</data>
<data>3187.837,2.765</data>
<data>3187.837,2.803</data>
<data>3187.837,2.794</data>
<data>3187.909,2.765</data>
<data>3187.909,2.757</data>
<data>3187.909,2.821</data>
<data>3187.909,2.701</data>
<data>3187.909,2.801</data>
<data>3187.972,2.681</data>
<data>3187.972,2.763</data>
<data>3187.972,2.803</data>
<data>3188,2.828</data>
<data>3188.034,2.787</data>
<data>3188.034,2.895</data>
<data>3188.095,2.828</data>
<data>3188.399,2.834</data>
<data>3188.399,3</data>
<data>3188.399,2.857</data>
<data>3188.649,2.839</data>
<data>3188.649,2.895</data>
<data>3188.666,2.89</data>
<data>3188.78,2.837</data>
<data>3188.78,2.928</data>
<data>3188.78,2.832</data>
<data>3188.78,2.837</data>
<data>3188.78,3.036</data>
<data>3189.003,3.028</data>
<data>3189.391,2.907</data>
<data>3189.391,2.677</data>
<data>3189.391,2.583</data>
<data>3189.391,2.841</data>
<data>3189.391,2.857</data>
<data>3189.391,3.218</data>
<data>3190.045,3.204</data>
<data>3190.045,3.002</data>
<data>3190.045,3.159</data>
<data>3190.045,3.309</data>
<data>3190.045,2.938</data>
<data>3190.045,3.107</data>
<data>3190.045,3.21</data>
<data>3190.045,3.139</data>
<data>3190.045,2.945</data>
<data>3190.045,3.134</data>
<data>3190.045,3.198</data>
<data>3190.155,3.145</data>
<data>3190.155,3.17</data>
<data>3190.495,3.192</data>
<data>3190.495,3.207</data>
<data>3190.495,2.864</data>
<data>3190.495,3.142</data>
<data>3190.495,3.192</data>
<data>3190.515,3.733</data>
<data>3190.535,3.088</data>
<data>3190.535,3.12</data>
<data>3190.535,3.049</data>
<data>3190.535,3.077</data>
<data>3190.658,3.002</data>
<data>3190.658,3.096</data>
<data>3190.658,3.085</data>
<data>3190.658,3.647</data>
<data>3190.658,3.173</data>
<data>3190.658,2.874</data>
<data>3190.658,2.987</data>
<data>3190.658,2.83</data>
<data>3190.658,3.067</data>
<data>3190.658,3.164</data>
<data>3190.658,2.83</data>
<data>3190.658,3.067</data>
<data>3190.658,3.164</data>
<data>3190.658,2.874</data>
<data>3190.658,2.987</data>
<data>3190.658,2.83</data>
<data>3190.658,3.067</data>
<data>3190.658,3.164</data>
<data>3190.658,2.874</data>
<data>3190.658,2.987</data>
<data>3190.658,2.83</data>
<data>3190.658,3.067</data>
<data>3190.658,3.164</data>
<data>3190.658,3.176</data>
<data>3190.658,3.03</data>
<data>3190.658,3</data>
<data>3190.658,3.21</data>
<data>3190.658,3.406</data>
<data>3190.712,3.475</data>
<data>3190.712,3.08</data>
<data>3190.712,3.093</data>
<data>3190.712,3.038</data>
<data>3190.712,3.112</data>
<data>3190.743,3.051</data>
<data>3190.777,3.077</data>
<data>3190.777,2.957</data>
<data>3190.777,3.069</data>
<data>3190.777,3.067</data>
<data>3190.777,3.083</data>
<data>3190.777,3.033</data>
<data>3190.777,3.083</data>
<data>3190.777,3.012</data>
<data>3191.027,3.041</data>
<data>3191.027,2.957</data>
<data>3191.072,3.02</data>
<data>3191.072,3.067</data>
<data>3191.119,2.94</data>
<data>3191.119,3.104</data>
<data>3191.119,3.181</data>
<data>3191.119,3.167</data>
<data>3191.264,3.046</data>
<data>3191.264,3.139</data>
<data>3191.264,3.115</data>
<data>3191.264,2.776</data>
<data>3191.264,3.244</data>
<data>3191.264,3.069</data>
<data>3191.399,3.025</data>
<data>3191.399,3.282</data>
<data>3191.399,2.945</data>
<data>3191.399,3.043</data>
<data>3191.742,3.075</data>
<data>3192.68,3.349</data>
<data>3193.568,3.847</data>
<data>3193.911,3.589</data>
<data>3193.911,3.571</data>
<data>3194.614,3.393</data>
<data>3196.164,3.312</data>
<data>3197.217,2.895</data>
<data>3197.267,2.931</data>
<data>3198.201,2.363</data>
<data>3199.425,3.334</data>
<data>3200.035,3.156</data>
<data>3201.972,3.297</data>
<data>3202.744,3.204</data>
<data>3203.832,3.589</data>
<data>3204.851,3.752</data>
<data>3206.297,3.005</data>
<data>3207.293,2.874</data>
<data>3208.554,3</data>
<data>3209.03,3.077</data>
<data>3210.511,3.043</data>
<data>3211.406,3.187</data>
<data>3212.583,3.791</data>
<data>3213.113,3.309</data>
<data>3213.707,3.448</data>
<data>3213.963,3.268</data>
<data>3214.648,3.468</data>
<data>3215.51,3.297</data>
<data>3215.703,3.346</data>
<data>3215.935,3.495</data>
<data>3216.518,3.488</data>
<data>3216.537,3.592</data>
<data>3216.814,3.628</data>
<data>3216.902,3.725</data>
<data>3219.549,0.135</data>
<data>3219.549,4.137</data>
<data>3219.549,4.118</data>
<data>3219.658,4.009</data>
<data>3219.966,3.868</data>
<data>3220.895,4.268</data>
<data>3220.953,4.228</data>
<data>3222.365,4.981</data>
<data>3223.212,5.267</data>
<data>3226.408,6.425</data>
<data>3227.748,5.836</data>
<data>3227.9,5.579</data>
<data>3228.054,5.313</data>
<data>3228.062,5.243</data>
<data>3228.062,4.829</data>
<data>3228.179,5.501</data>
<data>3228.179,5.836</data>
<data>3228.179,5.337</data>
<data>3228.179,5.553</data>
<data>3228.484,5.614</data>
<data>3228.484,5.468</data>
<data>3228.484,5.983</data>
<data>3228.484,5.393</data>
<data>3228.484,5.597</data>
<data>3228.484,5.029</data>
<data>3228.484,5.983</data>
<data>3228.484,4.591</data>
<data>3228.518,4.92</data>
<data>3228.518,6.563</data>
<data>3228.518,4.71</data>
<data>3228.572,5.131</data>
<data>3228.967,5.313</data>
<data>3229.298,5.443</data>
<data>3229.298,5.953</data>
<data>3229.298,5.953</data>
<data>3229.721,5.51</data>
<data>3229.721,5.51</data>
<data>3230.303,5.704</data>
<data>3230.303,5.704</data>
<data>3230.885,5.476</data>
<data>3230.885,5.476</data>
<data>3231.829,4.673</data>
<data>3232.124,4.759</data>
<data>3233.467,5.058</data>
<data>3233.467,5.067</data>
<data>3233.467,5.067</data>
<data>3234.087,5.913</data>
<data>3235.96,5.345</data>
<data>3237.687,5.41</data>
<data>3238.261,4.573</data>
<data>3238.287,5.009</data>
<data>3238.519,4.855</data>
<data>3239.349,4.248</data>
<data>3239.698,4.194</data>
<data>3240.296,4.249</data>
<data>3240.73,4.213</data>
<data>3241.079,4.022</data>
<data>3241.079,3.617</data>
<data>3241.556,4.053</data>
<data>3241.556,4.053</data>
<data>3241.556,4.053</data>
<data>3241.745,4.026</data>
<data>3241.745,4.026</data>
<data>3241.745,4.026</data>
<data>3241.745,4.026</data>
<data>3241.765,4.263</data>
<data>3241.94,4.423</data>
<data>3241.94,4.423</data>
<data>3242.67,2.535</data>
<data>3242.67,4.244</data>
<data>3242.67,2.547</data>
<data>3242.67,4.152</data>
<data>3242.67,2.535</data>
<data>3242.67,4.244</data>
<data>3242.67,4.152</data>
<data>3242.67,2.535</data>
<data>3242.67,4.244</data>
<data>3242.67,4.152</data>
<data>3242.67,4.195</data>
<data>3242.67,2.535</data>
<data>3242.67,4.244</data>
<data>3242.67,2.547</data>
<data>3242.67,4.152</data>
<data>3242.715,4.195</data>
<data>3242.763,3.992</data>
<data>3242.763,3.992</data>
<data>3242.934,4.054</data>
<data>3242.934,4.054</data>
<data>3243.033,3.983</data>
<data>3243.045,4.569</data>
<data>3243.09,4.507</data>
<data>3243.321,4.569</data>
<data>3243.615,4.414</data>
<data>3243.739,4.244</data>
<data>3244.475,4.446</data>
<data>3244.718,4.142</data>
<data>3244.995,4.314</data>
<data>3245.228,4.361</data>
<data>3245.269,4.219</data>
<data>3245.388,4.382</data>
<data>3246.162,4.005</data>
<data>3246.797,4.633</data>
<data>3248.285,4.78</data>
<data>3249.572,5.018</data>
<data>3250.058,3.932</data>
<data>3250.058,5.018</data>
<data>3250.667,4.209</data>
<data>3251.014,3.873</data>
<data>3251.63,4.105</data>
<data>3251.932,3.757</data>
<data>3252.212,3.662</data>
<data>3252.551,3.768</data>
<data>3253.96,3.45</data>
<data>3254.674,3.086</data>
<data>3255.328,3.199</data>
<data>3255.546,3.011</data>
<data>3256.614,3.338</data>
<data>3257.419,3.014</data>
<data>3259.013,2.804</data>
<data>3259.923,3.191</data>
<data>3261.41,3.927</data>
<data>3262.363,3.865</data>
<data>3263.691,3.108</data>
<data>3264.166,3.146</data>
<data>3265.428,3.243</data>
<data>3266.559,2.937</data>
<data>3267.688,2.758</data>
<data>3268.7,2.84</data>
<data>3270.563,3.45</data>
<data>3271.378,3.289</data>
<data>3272.098,2.784</data>
<data>3272.348,2.835</data>
<data>3272.573,3.138</data>
<data>3272.924,2.84</data>
<data>3273.348,2.766</data>
<data>3274.052,2.78</data>
<data>3274.146,2.751</data>
<data>3274.565,2.835</data>
<data>3276.06,2.609</data>
<data>3276.06,2.586</data>
<data>3277.153,2.204</data>
<data>3277.366,2.226</data>
<data>3278.425,2.124</data>
<data>3278.499,2.22</data>
<data>3279.751,2.173</data>
<data>3279.8,2.012</data>
<data>3279.808,2.108</data>
<data>3280.934,1.989</data>
<data>3281.366,1.975</data>
<data>3281.526,1.964</data>
<data>3281.818,2.003</data>
<data>3282.421,1.919</data>
<data>3282.878,1.91</data>
<data>3283.389,1.913</data>
<data>3284.176,1.838</data>
<data>3284.774,1.822</data>
<data>3285.739,1.822</data>
<data>3286.134,1.864</data>
<data>3286.54,1.807</data>
<data>3286.962,1.795</data>
<data>3287.031,1.759</data>
<data>3287.189,1.722</data>
<data>3287.391,1.741</data>
<data>3287.657,1.68</data>
<data>3287.822,1.684</data>
<data>3288.136,1.695</data>
<data>3288.688,1.681</data>
<data>3288.839,1.671</data>
<data>3289.069,1.637</data>
<data>3289.124,1.646</data>
<data>3289.362,1.568</data>
<data>3290.219,1.575</data>
<data>3290.229,1.599</data>
<data>3290.46,1.592</data>
<data>3291.038,1.555</data>
<data>3291.478,1.45</data>
<data>3291.484,1.596</data>
<data>3291.638,1.429</data>
<data>3291.855,1.58</data>
<data>3292.05,1.543</data>
<data>3292.05,1.548</data>
<data>3292.05,1.501</data>
<data>3292.243,1.468</data>
<data>3292.723,1.436</data>
<data>3292.835,1.467</data>
<data>3292.916,1.436</data>
<data>3292.995,1.436</data>
<data>3293.044,1.414</data>
<data>3293.542,1.402</data>
<data>3293.595,1.363</data>
<data>3293.751,1.359</data>
<data>3294.096,1.333</data>
<data>3294.096,1.333</data>
<data>3294.57,1.328</data>
<data>3294.735,1.328</data>
<data>3294.892,1.316</data>
<data>3294.892,1.316</data>
<data>3295.106,1.31</data>
<data>3295.116,1.31</data>
<data>3295.25,1.319</data>
<data>3295.25,1.319</data>
<data>3295.758,1.494</data>
<data>3295.773,1.322</data>
<data>3295.773,1.322</data>
<data>3296.004,0.633</data>
<data>3296.007,1.335</data>
<data>3296.48,1.369</data>
<data>3296.808,1.384</data>
<data>3297.27,1.407</data>
<data>3297.705,1.301</data>
<data>3298.181,1.333</data>
<data>3298.241,1.326</data>
<data>3298.425,1.317</data>
<data>3298.688,1.317</data>
<data>3298.688,1.317</data>
<data>3298.688,1.317</data>
<data>3299.147,1.295</data>
<data>3299.253,1.288</data>
<data>3299.336,1.288</data>
<data>3299.336,1.288</data>
<data>3300.019,1.247</data>
<data>3300.028,1.293</data>
<data>3300.028,1.369</data>
<data>3300.028,1.293</data>
<data>3300.028,1.293</data>
<data>3300.028,1.369</data>
<data>3300.055,1.308</data>
<data>3300.118,1.369</data>
<data>3300.226,1.294</data>
<data>3300.746,1.269</data>
<data>3301.034,1.381</data>
<data>3301.051,1.406</data>
<data>3301.079,1.271</data>
<data>3301.195,1.394</data>
<data>3301.195,1.294</data>
<data>3301.195,1.393</data>
<data>3301.195,1.288</data>
<data>3301.195,1.348</data>
<data>3301.206,1.34</data>
<data>3301.221,1.27</data>
<data>3301.315,8.07</data>
<data>3301.661,1.296</data>
<data>3301.686,1.338</data>
<data>3301.784,1.326</data>
<data>3302.01,1.32</data>
<data>3302.277,1.345</data>
<data>3302.372,1.297</data>
<data>3302.684,1.269</data>
<data>3302.684,1.292</data>
<data>3302.797,1.214</data>
<data>3303.41,1.291</data>
<data>3304.539,1.228</data>
<data>3304.539,1.262</data>
<data>3304.654,1.279</data>
<data>3305.237,1.372</data>
<data>3306.333,1.828</data>
<data>3307.469,1.412</data>
<data>3308.05,1.4</data>
<data>3308.411,1.382</data>
<data>3309.003,1.281</data>
<data>3309.129,1.267</data>
<data>3309.204,1.284</data>
<data>3309.335,1.324</data>
<data>3309.544,1.326</data>
<data>3309.563,1.323</data>
<data>3309.727,1.302</data>
<data>3309.727,1.305</data>
<data>3309.806,1.307</data>
<data>3310.696,1.291</data>
<data>3310.822,1.281</data>
<data>3310.867,1.29</data>
<data>3310.867,1.276</data>
<data>3310.899,1.298</data>
<data>3310.899,1.268</data>
<data>3310.899,1.285</data>
<data>3311.064,1.265</data>
<data>3311.064,1.271</data>
<data>3311.16,1.282</data>
<data>3311.16,1.27</data>
<data>3311.16,1.274</data>
<data>3311.16,1.273</data>
<data>3311.439,1.272</data>
<data>3311.682,1.242</data>
<data>3312.039,1.21</data>
<data>3312.105,1.229</data>
<data>3312.203,1.257</data>
<data>3312.399,1.223</data>
<data>3312.717,1.248</data>
<data>3313.163,1.272</data>
<data>3313.163,1.281</data>
<data>3313.163,1.28</data>
<data>3313.163,1.292</data>
<data>3313.163,1.298</data>
<data>3313.163,1.302</data>
<data>3313.163,1.321</data>
<data>3313.173,1.327</data>
<data>3313.319,1.344</data>
<data>3313.461,1.348</data>
<data>3313.461,1.352</data>
<data>3313.461,1.361</data>
<data>3313.461,1.355</data>
<data>3313.461,1.355</data>
<data>3313.461,1.356</data>
<data>3313.461,1.364</data>
<data>3313.461,1.366</data>
<data>3313.528,1.367</data>
<data>3313.528,1.379</data>
<data>3313.528,1.374</data>
<data>3313.528,1.378</data>
<data>3313.941,1.375</data>
<data>3313.941,1.376</data>
<data>3313.941,1.369</data>
<data>3313.941,1.378</data>
<data>3313.941,1.372</data>
<data>3313.941,1.368</data>
<data>3313.941,1.376</data>
<data>3313.941,1.363</data>
<data>3313.941,1.376</data>
<data>3313.941,1.374</data>
<data>3313.941,1.361</data>
<data>3313.941,1.368</data>
<data>3313.941,1.359</data>
<data>3313.941,1.362</data>
<data>3313.941,1.364</data>
<data>3313.941,1.362</data>
<data>3313.941,1.351</data>
<data>3313.941,1.35</data>
<data>3313.941,1.358</data>
<data>3313.941,1.344</data>
<data>3313.941,1.343</data>
<data>3313.987,1.339</data>
<data>3313.987,1.345</data>
<data>3313.987,1.35</data>
<data>3313.987,1.351</data>
<data>3314.019,1.353</data>
<data>3314.019,1.356</data>
<data>3314.019,1.35</data>
<data>3314.174,1.359</data>
<data>3314.174,1.36</data>
<data>3314.174,1.371</data>
<data>3314.247,1.354</data>
<data>3314.318,1.367</data>
<data>3314.318,1.365</data>
<data>3314.864,1.345</data>
<data>3314.864,1.339</data>
<data>3314.864,1.339</data>
<data>3314.864,1.333</data>
<data>3314.864,1.328</data>
<data>3314.864,1.339</data>
<data>3314.864,1.346</data>
<data>3314.864,1.34</data>
<data>3314.864,1.327</data>
<data>3314.864,1.325</data>
<data>3314.864,1.339</data>
<data>3314.864,1.336</data>
<data>3314.864,1.308</data>
<data>3314.864,1.316</data>
<data>3314.864,1.342</data>
<data>3314.887,1.299</data>
<data>3314.887,1.324</data>
<data>3314.916,1.312</data>
<data>3315.038,1.366</data>
<data>3315.038,1.35</data>
<data>3315.038,1.366</data>
<data>3315.038,1.357</data>
<data>3315.038,1.338</data>
<data>3315.038,1.375</data>
<data>3315.083,1.339</data>
<data>3315.166,0.414</data>
<data>3315.166,1.353</data>
<data>3315.275,1.278</data>
<data>3315.275,1.304</data>
<data>3315.289,1.292</data>
<data>3315.289,1.28</data>
<data>3315.31,1.27</data>
<data>3315.324,1.227</data>
<data>3315.633,1.205</data>
<data>3315.633,1.182</data>
<data>3315.728,1.185</data>
<data>3315.728,1.165</data>
<data>3316.004,1.132</data>
<data>3316.155,1.202</data>
<data>3316.155,1.185</data>
<data>3316.155,1.168</data>
<data>3316.155,1.165</data>
<data>3316.155,1.206</data>
<data>3316.219,1.182</data>
<data>3316.256,1.189</data>
<data>3316.298,1.139</data>
<data>3316.342,1.128</data>
<data>3316.393,1.113</data>
<data>3316.393,1.159</data>
<data>3316.732,1.151</data>
<data>3316.732,1.111</data>
<data>3316.732,1.197</data>
<data>3316.732,1.19</data>
<data>3316.732,1.205</data>
<data>3316.732,1.183</data>
<data>3316.732,1.224</data>
<data>3316.732,1.228</data>
<data>3316.876,1.183</data>
<data>3316.876,1.235</data>
<data>3316.876,1.184</data>
<data>3316.897,1.14</data>
<data>3316.994,1.229</data>
<data>3316.994,1.207</data>
<data>3316.994,1.198</data>
<data>3317.314,1.239</data>
<data>3317.556,1.224</data>
<data>3317.751,1.236</data>
<data>3317.751,1.26</data>
<data>3317.785,1.229</data>
<data>3317.963,1.171</data>
<data>3317.963,1.174</data>
<data>3318.044,1.173</data>
<data>3318.044,1.17</data>
<data>3318.053,1.144</data>
<data>3318.053,1.173</data>
<data>3318.068,1.174</data>
<data>3318.087,1.212</data>
<data>3318.09,1.208</data>
<data>3318.09,1.155</data>
<data>3318.128,1.178</data>
<data>3318.167,1.167</data>
<data>3318.22,1.165</data>
<data>3318.22,1.149</data>
<data>3318.35,1.165</data>
<data>3318.431,1.169</data>
<data>3318.431,1.181</data>
<data>3318.586,1.151</data>
<data>3318.586,1.178</data>
<data>3318.874,1.23</data>
<data>3318.874,1.229</data>
<data>3318.874,1.244</data>
<data>3318.998,1.235</data>
<data>3319.107,1.228</data>
<data>3319.107,1.229</data>
<data>3319.107,1.257</data>
<data>3319.126,1.256</data>
<data>3319.126,1.285</data>
<data>3319.16,1.197</data>
<data>3319.22,1.304</data>
<data>3319.49,1.228</data>
<data>3319.49,1.246</data>
<data>3319.529,0.483</data>
<data>3319.529,1.29</data>
<data>3319.529,1.315</data>
<data>3319.529,1.324</data>
<data>3319.529,0.487</data>
<data>3319.529,1.246</data>
<data>3319.529,1.298</data>
<data>3319.726,1.311</data>
<data>3319.792,1.14</data>
<data>3319.924,1.279</data>
<data>3320.192,1.158</data>
<data>3320.314,1.228</data>
<data>3320.371,1.212</data>
<data>3320.371,1.174</data>
<data>3320.371,1.15</data>
<data>3320.371,1.241</data>
<data>3320.371,1.203</data>
<data>3320.371,1.187</data>
<data>3320.371,1.136</data>
<data>3320.371,1.144</data>
<data>3320.532,1.151</data>
<data>3320.532,1.147</data>
<data>3320.532,1.13</data>
<data>3320.532,1.133</data>
<data>3320.598,1.104</data>
<data>3320.598,1.14</data>
<data>3320.774,1.168</data>
<data>3320.889,1.103</data>
<data>3320.889,1.118</data>
<data>3320.936,1.123</data>
<data>3321.005,1.166</data>
<data>3321.059,1.095</data>
<data>3321.192,1.125</data>
<data>3321.225,1.105</data>
<data>3321.225,1.081</data>
<data>3321.225,1.118</data>
<data>3321.225,1.07</data>
<data>3321.225,1.065</data>
<data>3321.225,1.069</data>
<data>3321.232,1.122</data>
<data>3321.232,1.088</data>
<data>3321.309,1.091</data>
<data>3321.309,1.072</data>
<data>3321.367,1.069</data>
<data>3321.367,1.095</data>
<data>3321.367,1.12</data>
<data>3321.367,1.056</data>
<data>3321.367,1.055</data>
<data>3321.542,1.063</data>
<data>3321.542,1.106</data>
<data>3321.6,1.076</data>
<data>3321.6,1.138</data>
<data>3321.6,1.053</data>
<data>3321.6,1.079</data>
<data>3321.6,1.03</data>
<data>3321.865,0.093</data>
<data>3321.865,1.055</data>
<data>3322.021,1.106</data>
<data>3322.021,1.057</data>
<data>3322.021,1.076</data>
<data>3322.021,1.061</data>
<data>3322.021,1.058</data>
<data>3322.059,1.02</data>
<data>3322.059,1.068</data>
<data>3322.059,1.004</data>
<data>3322.059,1.092</data>
<data>3322.418,1.07</data>
<data>3322.418,1.037</data>
<data>3322.418,1.022</data>
<data>3322.418,1.015</data>
<data>3322.418,1.024</data>
<data>3322.418,1.018</data>
<data>3322.418,1.031</data>
<data>3322.418,1.015</data>
<data>3322.488,1.057</data>
<data>3322.488,1.055</data>
<data>3322.488,1.028</data>
<data>3322.488,1.005</data>
<data>3322.594,1.014</data>
<data>3322.601,1.006</data>
<data>3322.781,1.046</data>
<data>3322.781,1.046</data>
<data>3322.845,0.997</data>
<data>3322.861,1.063</data>
<data>3322.861,1.047</data>
<data>3322.861,0.991</data>
<data>3322.911,1.041</data>
<data>3323.056,1</data>
<data>3323.056,1.038</data>
<data>3323.056,1</data>
<data>3323.056,1.025</data>
<data>3323.201,0.996</data>
<data>3323.21,0.973</data>
<data>3323.333,1.01</data>
<data>3323.675,1.029</data>
<data>3323.675,0.957</data>
<data>3323.702,0.988</data>
<data>3323.827,1.598</data>
<data>3323.827,0.976</data>
<data>3323.827,0.996</data>
<data>3323.827,0.965</data>
<data>3323.962,1</data>
<data>3323.962,0.961</data>
<data>3323.962,0.97</data>
<data>3323.962,0.995</data>
<data>3323.962,0.998</data>
<data>3323.962,0.992</data>
<data>3323.962,0.995</data>
<data>3323.962,0.952</data>
<data>3323.962,0.963</data>
<data>3323.962,0.942</data>
<data>3323.962,0.961</data>
<data>3323.962,0.951</data>
<data>3323.962,0.954</data>
<data>3323.962,0.97</data>
<data>3323.962,1.003</data>
<data>3323.962,0.963</data>
<data>3323.962,0.999</data>
<data>3323.962,0.995</data>
<data>3323.962,0.972</data>
<data>3324.071,0.996</data>
<data>3324.071,0.999</data>
<data>3324.071,1.001</data>
<data>3324.071,0.964</data>
<data>3324.071,1.028</data>
<data>3324.071,1.024</data>
<data>3324.071,0.972</data>
<data>3324.238,0.986</data>
<data>3324.238,0.966</data>
<data>3324.238,0.94</data>
<data>3324.238,0.999</data>
<data>3324.238,0.997</data>
<data>3324.238,1.001</data>
<data>3324.241,0.952</data>
<data>3324.241,1.006</data>
<data>3324.241,1.008</data>
<data>3324.251,0.935</data>
<data>3324.251,1.004</data>
<data>3324.251,0.967</data>
<data>3324.335,0.407</data>
<data>3324.338,0.968</data>
<data>3324.338,0.984</data>
<data>3324.338,0.962</data>
<data>3324.368,1.005</data>
<data>3324.369,0.991</data>
<data>3324.385,1.001</data>
<data>3324.385,1.004</data>
<data>3324.385,0.98</data>
<data>3324.409,0.984</data>
<data>3324.409,0.984</data>
<data>3324.432,0.989</data>
<data>3324.432,0.951</data>
<data>3324.432,0.961</data>
<data>3324.432,0.933</data>
<data>3324.463,0.973</data>
<data>3324.538,1.029</data>
<data>3324.693,1.032</data>
<data>3324.693,0.976</data>
<data>3324.785,0.973</data>
<data>3324.967,0.923</data>
<data>3324.967,0.939</data>
<data>3325.399,0.912</data>
<data>3326.026,0.897</data>
<data>3326.148,0.89</data>
<data>3326.169,0.915</data>
<data>3326.29,0.914</data>
<data>3326.429,0.948</data>
<data>3326.631,0.926</data>
<data>3326.699,0.921</data>
<data>3326.799,0.882</data>
<data>3326.799,0.89</data>
<data>3326.824,0.909</data>
<data>3326.828,0.922</data>
<data>3326.893,0.936</data>
<data>3326.893,0.936</data>
<data>3326.935,0.904</data>
<data>3327.114,0.92</data>
<data>3327.114,0.946</data>
<data>3327.135,0.882</data>
<data>3327.297,0.893</data>
<data>3327.297,0.939</data>
<data>3327.302,0.899</data>
<data>3327.338,0.896</data>
<data>3327.338,0.887</data>
<data>3327.338,0.91</data>
<data>3327.367,0.934</data>
<data>3327.367,0.901</data>
<data>3327.367,0.955</data>
<data>3327.504,0.919</data>
<data>3327.504,0.921</data>
<data>3327.504,0.921</data>
<data>3327.558,0.921</data>
<data>3327.558,0.886</data>
<data>3327.558,0.91</data>
<data>3327.643,0.915</data>
<data>3327.643,0.882</data>
<data>3327.643,0.949</data>
<data>3327.643,0.929</data>
<data>3327.643,0.938</data>
<data>3327.727,0.858</data>
<data>3327.727,0.894</data>
<data>3327.727,0.751</data>
<data>3327.727,0.95</data>
<data>3327.727,0.905</data>
<data>3327.727,0.909</data>
<data>3327.727,0.956</data>
<data>3327.727,0.925</data>
<data>3327.727,0.858</data>
<data>3327.771,0.871</data>
<data>3327.771,0.927</data>
<data>3327.771,0.898</data>
<data>3327.771,0.948</data>
<data>3327.771,0.937</data>
<data>3327.771,0.937</data>
<data>3327.86,0.923</data>
<data>3327.86,0.923</data>
<data>3327.86,0.923</data>
<data>3327.86,0.87</data>
<data>3327.86,0.87</data>
<data>3327.86,0.87</data>
<data>3327.86,0.87</data>
<data>3327.86,0.923</data>
<data>3327.86,0.896</data>
<data>3327.86,0.887</data>
<data>3327.86,0.96</data>
<data>3327.86,0.908</data>
<data>3327.86,0.887</data>
<data>3327.86,0.902</data>
<data>3327.86,0.813</data>
<data>3327.86,0.87</data>
<data>3327.86,0.87</data>
<data>3327.86,0.87</data>
<data>3327.872,0.951</data>
<data>3327.872,0.951</data>
<data>3327.872,0.951</data>
<data>3327.872,0.915</data>
<data>3327.872,0.951</data>
<data>3327.872,0.915</data>
<data>3327.872,0.951</data>
<data>3327.872,0.915</data>
<data>3327.917,0.896</data>
<data>3327.917,0.893</data>
<data>3327.917,0.95</data>
<data>3327.917,0.903</data>
<data>3327.917,0.957</data>
<data>3327.917,0.934</data>
<data>3327.917,0.914</data>
<data>3327.917,0.886</data>
<data>3327.917,0.917</data>
<data>3327.917,0.94</data>
<data>3327.917,0.93</data>
<data>3327.917,0.919</data>
<data>3327.917,0.942</data>
<data>3327.917,0.942</data>
<data>3327.917,0.877</data>
<data>3327.957,0.952</data>
<data>3327.957,0.954</data>
<data>3327.957,0.904</data>
<data>3327.957,0.904</data>
<data>3327.977,0.945</data>
<data>3327.977,0.872</data>
<data>3327.977,0.911</data>
<data>3327.977,0.916</data>
<data>3327.977,0.911</data>
<data>3327.977,0.945</data>
<data>3328.014,0.996</data>
<data>3328.014,0.886</data>
<data>3328.014,0.871</data>
<data>3328.014,0.872</data>
<data>3328.014,0.959</data>
<data>3328.014,0.907</data>
<data>3328.014,0.893</data>
<data>3328.014,0.958</data>
<data>3328.014,0.944</data>
<data>3328.014,0.916</data>
<data>3328.014,0.967</data>
<data>3328.014,0.87</data>
<data>3328.014,0.78</data>
<data>3328.014,0.909</data>
<data>3328.087,0.998</data>
<data>3328.091,0.931</data>
<data>3328.274,0.879</data>
<data>3328.274,0.864</data>
<data>3328.274,0.84</data>
<data>3328.274,0.997</data>
<data>3328.274,0.919</data>
<data>3328.274,0.915</data>
<data>3328.274,0.871</data>
<data>3328.274,0.962</data>
<data>3328.274,0.941</data>
<data>3328.274,0.839</data>
<data>3328.274,0.859</data>
<data>3328.274,0.886</data>
<data>3328.274,0.848</data>
<data>3328.274,0.918</data>
<data>3328.274,0.877</data>
<data>3328.335,0.862</data>
<data>3328.335,0.999</data>
<data>3328.335,0.971</data>
<data>3328.335,0.844</data>
</logData>
    <commonData>
      <nameSource>SC001</nameSource>
      <dTimStamp>2007-06-11T14:23:25.5850000+02:00</dTimStamp>
      <dTimCreation>2007-06-11T13:09:14.9290000+02:00</dTimCreation>
      <dTimLastChange>2007-06-11T13:09:14.9610000+02:00</dTimLastChange>
      <itemState>Actual</itemState>
    </commonData>
  </log>
</logs>
